strawberry_django/__init__.py
strawberry_django/apps.py
strawberry_django/arguments.py
strawberry_django/descriptors.py
strawberry_django/exceptions.py
strawberry_django/filters.py
strawberry_django/optimizer.py
strawberry_django/ordering.py
strawberry_django/pagination.py
strawberry_django/permissions.py
strawberry_django/py.typed
strawberry_django/queryset.py
strawberry_django/resolvers.py
strawberry_django/routers.py
strawberry_django/settings.py
strawberry_django/type.py
strawberry_django/auth/__init__.py
strawberry_django/auth/mutations.py
strawberry_django/auth/queries.py
strawberry_django/auth/utils.py
strawberry_django/extensions/__init__.py
strawberry_django/extensions/django_cache_base.py
strawberry_django/extensions/django_validation_cache.py
strawberry_django/fields/__init__.py
strawberry_django/fields/base.py
strawberry_django/fields/field.py
strawberry_django/fields/filter_order.py
strawberry_django/fields/filter_types.py
strawberry_django/fields/types.py
strawberry_django/integrations/__init__.py
strawberry_django/integrations/guardian.py
strawberry_django/management/__init__.py
strawberry_django/management/commands/__init__.py
strawberry_django/management/commands/export_schema.py
strawberry_django/middlewares/__init__.py
strawberry_django/middlewares/debug_toolbar.py
strawberry_django/mutations/__init__.py
strawberry_django/mutations/fields.py
strawberry_django/mutations/mutations.py
strawberry_django/mutations/resolvers.py
strawberry_django/mutations/types.py
strawberry_django/relay/__init__.py
strawberry_django/relay/cursor_connection.py
strawberry_django/relay/list_connection.py
strawberry_django/relay/utils.py
strawberry_django/templates/strawberry_django/debug_toolbar.html
strawberry_django/test/__init__.py
strawberry_django/test/client.py
strawberry_django/utils/__init__.py
strawberry_django/utils/inspect.py
strawberry_django/utils/patches.py
strawberry_django/utils/pyutils.py
strawberry_django/utils/query.py
strawberry_graphql_django-0.73.1.dist-info/METADATA
strawberry_graphql_django-0.73.1.dist-info/WHEEL
strawberry_graphql_django-0.73.1.dist-info/licenses/LICENSE
strawberry_graphql_django-0.73.1.dist-info/RECORD
