Metadata-Version: 2.4
Name: strawberry-graphql-django
Version: 0.73.1
Summary: Strawberry GraphQL Django extension
Project-URL: homepage, https://strawberry.rocks/docs/django
Project-URL: repository, https://github.com/strawberry-graphql/strawberry-django
Project-URL: documentation, https://strawberry.rocks/docs/django
Author-email: Lauri Hintsala <lauri.hintsala@verkkopaja.fi>, Thiago Bellini Ribeiro <thiago@bellini.dev>
Maintainer-email: Thiago Bellini Ribeiro <thiago@bellini.dev>
License: MIT
License-File: LICENSE
Keywords: api,django,graphql,strawberry-graphql
Classifier: Environment :: Web Environment
Classifier: Framework :: Django
Classifier: Framework :: Django :: 4.2
Classifier: Framework :: Django :: 5.0
Classifier: Framework :: Django :: 5.1
Classifier: Framework :: Django :: 5.2
Classifier: Framework :: Django :: 6.0
Classifier: Intended Audience :: Developers
Classifier: License :: OSI Approved :: MIT License
Classifier: Operating System :: OS Independent
Classifier: Programming Language :: Python
Classifier: Programming Language :: Python :: 3
Classifier: Programming Language :: Python :: 3.10
Classifier: Programming Language :: Python :: 3.11
Classifier: Programming Language :: Python :: 3.12
Classifier: Programming Language :: Python :: 3.13
Classifier: Programming Language :: Python :: 3.14
Requires-Python: <4.0,>=3.10
Requires-Dist: asgiref>=3.8
Requires-Dist: django>=4.2
Requires-Dist: strawberry-graphql>=0.288.0
Provides-Extra: debug-toolbar
Requires-Dist: django-debug-toolbar>=6.0.0; extra == 'debug-toolbar'
Provides-Extra: enum
Requires-Dist: django-choices-field>=2.2.2; extra == 'enum'
